stTransfer/__init__.py
stTransfer/stTransfer/Transfer_entry.py
stTransfer/stTransfer/__init__.py
stTransfer/stTransfer/_settings.py
stTransfer/stTransfer/cell_type_ann_model.py
stTransfer/stTransfer/focal_loss.py
stTransfer/stTransfer/scTrain_entry.py
stTransfer/stTransfer/vae.py
stTransfer-1.0.25.dist-info/LICENSE
stTransfer-1.0.25.dist-info/METADATA
stTransfer-1.0.25.dist-info/WHEEL
stTransfer-1.0.25.dist-info/top_level.txt
stTransfer-1.0.25.dist-info/RECORD
