Metadata-Version: 2.1
Name: stTransfer
Version: 1.0.25
Summary: Transfer learning for spatial transcriptomics data and single-cell RNA-seq data.
Home-page: https://github.com/zepoch/stTransfer.git
Author: zhoutao
Author-email: zhotoa@foxmail.com
Classifier: Programming Language :: Python :: 3
Classifier: License :: OSI Approved :: MIT License
Classifier: Operating System :: OS Independent
Requires-Python: >=3.8
License-File: LICENSE
Requires-Dist: anndata>=0.8.0
Requires-Dist: matplotlib>=3.5.1
Requires-Dist: matplotlib-inline>=0.1.3
Requires-Dist: networkx>=2.7.1
Requires-Dist: numpy>=1.21.5
Requires-Dist: pandas>=1.4.2
Requires-Dist: scanpy>=1.9.1
Requires-Dist: scikit-learn>=1.0.2
Requires-Dist: scipy>=1.8.0
Requires-Dist: seaborn>=0.11.2
Requires-Dist: scvi-tools==0.17.0
Requires-Dist: xgboost>=2.0.0
